{
   "comments" : [],
   "name" : {
      "value" : "main",
      "position" : {
         "column" : 9,
         "line" : 1,
         "offset" : 8,
         "filename" : "fixtures/packages/qualifiedtype/qualified.go"
      },
      "kind" : "ident"
   },
   "imports" : [
      {
         "type" : "import",
         "specs" : [
            {
               "path" : "go/ast",
               "comments" : [],
               "name" : null,
               "type" : "import",
               "doc" : [],
               "position" : {
                  "line" : 3,
                  "column" : 8,
                  "filename" : "fixtures/packages/qualifiedtype/qualified.go",
                  "offset" : 21
               }
            }
         ],
         "kind" : "decl",
         "position" : {
            "column" : 1,
            "line" : 3,
            "offset" : 14,
            "filename" : "fixtures/packages/qualifiedtype/qualified.go"
         }
      }
   ],
   "declarations" : [
      {
         "position" : {
            "column" : 1,
            "line" : 3,
            "offset" : 14,
            "filename" : "fixtures/packages/qualifiedtype/qualified.go"
         },
         "kind" : "decl",
         "specs" : [
            {
               "doc" : [],
               "type" : "import",
               "position" : {
                  "offset" : 21,
                  "filename" : "fixtures/packages/qualifiedtype/qualified.go",
                  "column" : 8,
                  "line" : 3
               },
               "path" : "go/ast",
               "comments" : [],
               "name" : null
            }
         ],
         "type" : "import"
      },
      {
         "comments" : [],
         "results" : null,
         "position" : {
            "column" : 1,
            "line" : 5,
            "offset" : 31,
            "filename" : "fixtures/packages/qualifiedtype/qualified.go"
         },
         "body" : [],
         "name" : {
            "position" : {
               "column" : 6,
               "line" : 5,
               "offset" : 36,
               "filename" : "fixtures/packages/qualifiedtype/qualified.go"
            },
            "value" : "doit",
            "kind" : "ident"
         },
         "params" : [
            {
               "declared-type" : {
                  "type" : "identifier",
                  "value" : {
                     "value" : "Node",
                     "kind" : "ident",
                     "position" : {
                        "column" : 17,
                        "line" : 5,
                        "offset" : 47,
                        "filename" : "fixtures/packages/qualifiedtype/qualified.go"
                     }
                  },
                  "kind" : "type",
                  "position" : {
                     "filename" : "fixtures/packages/qualifiedtype/qualified.go",
                     "offset" : 43,
                     "line" : 5,
                     "column" : 13
                  },
                  "qualifier" : {
                     "kind" : "ident",
                     "value" : "ast",
                     "position" : {
                        "offset" : 43,
                        "filename" : "fixtures/packages/qualifiedtype/qualified.go",
                        "column" : 13,
                        "line" : 5
                     }
                  }
               },
               "tag" : null,
               "names" : [
                  {
                     "kind" : "ident",
                     "value" : "a",
                     "position" : {
                        "column" : 11,
                        "line" : 5,
                        "offset" : 41,
                        "filename" : "fixtures/packages/qualifiedtype/qualified.go"
                     }
                  }
               ],
               "kind" : "field"
            }
         ],
         "kind" : "decl",
         "type" : "function"
      },
      {
         "kind" : "decl",
         "type" : "function",
         "params" : [],
         "name" : {
            "position" : {
               "line" : 9,
               "column" : 6,
               "filename" : "fixtures/packages/qualifiedtype/qualified.go",
               "offset" : 64
            },
            "value" : "main",
            "kind" : "ident"
         },
         "position" : {
            "filename" : "fixtures/packages/qualifiedtype/qualified.go",
            "offset" : 59,
            "line" : 9,
            "column" : 1
         },
         "body" : [],
         "comments" : [],
         "results" : null
      }
   ],
   "kind" : "file",
   "all-comments" : []
}
